eta_utility/__init__.py
eta_utility/connectors/__init__.py
eta_utility/connectors/base_classes.py
eta_utility/connectors/common.py
eta_utility/connectors/cumulocity.py
eta_utility/connectors/emonio.py
eta_utility/connectors/eneffco.py
eta_utility/connectors/entso_e.py
eta_utility/connectors/forecast_solar.py
eta_utility/connectors/live_connect.py
eta_utility/connectors/modbus.py
eta_utility/connectors/node.py
eta_utility/connectors/opc_ua.py
eta_utility/connectors/sub_handlers.py
eta_utility/connectors/util.py
eta_utility/connectors/wetterdienst_connection.py
eta_utility/eta_x/__init__.py
eta_utility/eta_x/agents/__init__.py
eta_utility/eta_x/agents/math_solver.py
eta_utility/eta_x/agents/nsga2.py
eta_utility/eta_x/agents/rule_based.py
eta_utility/eta_x/common/__init__.py
eta_utility/eta_x/common/callbacks.py
eta_utility/eta_x/common/common.py
eta_utility/eta_x/common/extractors.py
eta_utility/eta_x/common/policies.py
eta_utility/eta_x/common/processors.py
eta_utility/eta_x/common/schedules.py
eta_utility/eta_x/config.py
eta_utility/eta_x/envs/__init__.py
eta_utility/eta_x/envs/base_env.py
eta_utility/eta_x/envs/base_env_live.py
eta_utility/eta_x/envs/base_env_mpc.py
eta_utility/eta_x/envs/base_env_sim.py
eta_utility/eta_x/envs/julia_env.py
eta_utility/eta_x/envs/no_vec_env.py
eta_utility/eta_x/envs/state.py
eta_utility/eta_x/eta_x.py
eta_utility/ju_extensions/.JuliaFormatter.toml
eta_utility/ju_extensions/Manifest.toml
eta_utility/ju_extensions/Project.toml
eta_utility/ju_extensions/src/etax/agents/NSGA2.jl
eta_utility/ju_extensions/src/ju_extensions.jl
eta_utility/ju_extensions/src/utils.jl
eta_utility/ju_extensions/test/etax/agents/NSGA2.jl
eta_utility/ju_extensions/test/runtests.jl
eta_utility/py.typed
eta_utility/servers/__init__.py
eta_utility/servers/modbus.py
eta_utility/servers/opc_ua.py
eta_utility/simulators/__init__.py
eta_utility/simulators/fmu.py
eta_utility/timeseries/__init__.py
eta_utility/timeseries/dataframes.py
eta_utility-3.3.1.dist-info/LICENSE
eta_utility-3.3.1.dist-info/METADATA
eta_utility-3.3.1.dist-info/WHEEL
eta_utility-3.3.1.dist-info/entry_points.txt
eta_utility-3.3.1.dist-info/RECORD
