Metadata-Version: 2.3
Name: eta-utility
Version: 3.3.1
Summary: A framework for researching energy optimization of factory operations
License: BSD-2-Clause
Keywords: connectors,servers,simulators,industrial energy optimization,rolling horizon optimization
Author: Technical University of Darmstadt, Institute for Production Management, Technology and Machine Tools (PTW)
Author-email: info@ptw.tu-darmstadt.de
Requires-Python: >=3.9.2, <3.12
Classifier: Development Status :: 4 - Beta
Classifier: Intended Audience :: Developers
Classifier: Intended Audience :: Manufacturing
Classifier: Intended Audience :: Science/Research
Classifier: License :: OSI Approved :: BSD License
Classifier: Operating System :: OS Independent
Classifier: Programming Language :: Python :: 3
Classifier: Programming Language :: Python :: 3.10
Classifier: Programming Language :: Python :: 3.11
Classifier: Topic :: Scientific/Engineering :: Artificial Intelligence
Classifier: Topic :: Software Development :: Libraries
Provides-Extra: develop
Provides-Extra: eta-x
Provides-Extra: examples
Requires-Dist: asyncua-fork-for-eta-utility (==1.0.7)
Requires-Dist: attrs (>=23.1.0,<24.0.0)
Requires-Dist: black (>=23.7.0,<23.8.0) ; extra == "develop"
Requires-Dist: blacken_docs (>=1.16.0,<1.17.0) ; extra == "develop"
Requires-Dist: codespell (>=2.3.0,<3.0.0) ; extra == "develop"
Requires-Dist: cryptography (>=41.0.4,<42.0.0)
Requires-Dist: fmpy (>=0.3.5,<0.4.0)
Requires-Dist: gymnasium (==1.0.0) ; extra == "develop" or extra == "eta-x"
Requires-Dist: julia (>=0.6.2,<0.7.0) ; extra == "develop" or extra == "eta-x"
Requires-Dist: keyboard (>=0.13.5,<0.14.0) ; extra == "develop" or extra == "examples"
Requires-Dist: lxml (>=4.9.3,<5.0.0)
Requires-Dist: matplotlib (>=3.7.5,<3.8.0) ; extra == "develop" or extra == "examples"
Requires-Dist: mypy (>=1.9.0,<1.10.0) ; extra == "develop"
Requires-Dist: numpy (>=1.26.0,<1.27.0)
Requires-Dist: onnxruntime (==1.19.0) ; extra == "develop" or extra == "examples"
Requires-Dist: openpyxl (>=3.1.2,<4.0.0) ; extra == "develop"
Requires-Dist: pandas (>=2.2.2,<2.3.0)
Requires-Dist: pre-commit (>=3.4.0,<4.0.0) ; extra == "develop"
Requires-Dist: pygame (>=2.5.2,<3.0.0) ; extra == "develop" or extra == "examples"
Requires-Dist: pyglet (<2) ; extra == "develop" or extra == "examples"
Requires-Dist: pymodbustcp (==0.2.0)
Requires-Dist: pyomo (>=6.6.2,<6.7.0) ; extra == "develop" or extra == "eta-x"
Requires-Dist: pytest (>=7.4.2,<8.0.0) ; extra == "develop"
Requires-Dist: pytest-cov (>=6.0.0,<7.0.0) ; extra == "develop"
Requires-Dist: python-dateutil (>=2.8.2,<3.0.0)
Requires-Dist: python-dotenv (>=1.0.1,<2.0.0)
Requires-Dist: pyyaml (>=6.0.2,<7.0.0)
Requires-Dist: requests (>=2.31.0,<3.0.0)
Requires-Dist: requests-cache (>=1.2.0,<2.0.0)
Requires-Dist: ruff (>=0.9.6,<0.10.0) ; extra == "develop"
Requires-Dist: sphinx (>=7.1.2,<8.0.0) ; extra == "develop"
Requires-Dist: sphinx-copybutton (>=0.5.2,<0.6.0) ; extra == "develop"
Requires-Dist: sphinx-rtd-theme (>=1.3.0,<2.0.0) ; extra == "develop"
Requires-Dist: stable-baselines3 (>=2.4.0,<3.0.0) ; extra == "develop" or extra == "eta-x"
Requires-Dist: tensorboard (>=2.14.0,<2.15.0) ; extra == "develop" or extra == "eta-x"
Requires-Dist: toml (>=0.10.2,<0.11.0)
Requires-Dist: torch (==2.0.0) ; extra == "develop" or extra == "eta-x"
Requires-Dist: types-python-dateutil (>=2.8.19.14,<3.0.0.0) ; extra == "develop"
Requires-Dist: types-pytz (>=2024.1.0.20240203,<2025.0.0.0) ; extra == "develop"
Requires-Dist: types-requests (>=2.31.0.4,<3.0.0.0) ; extra == "develop"
Requires-Dist: wetterdienst (>=0.88.0,<0.89.0)
Requires-Dist: xlrd (>=2.0.1,<3.0.0)
Project-URL: Documentation, https://eta-utility.readthedocs.io/
Project-URL: Homepage, https://www.ptw.tu-darmstadt.de
Project-URL: Repository, https://github.com/PTW-TUDa/eta_utility/
Project-URL: issues, https://git.ptw.maschinenbau.tu-darmstadt.de/eta-fabrik/public/eta-utility/-/issues
